rijksdriehoek/__init__.py
rijksdriehoek/rijksdriehoek.py
rijksdriehoek-0.0.1.dist-info/DESCRIPTION.rst
rijksdriehoek-0.0.1.dist-info/METADATA
rijksdriehoek-0.0.1.dist-info/RECORD
rijksdriehoek-0.0.1.dist-info/WHEEL
rijksdriehoek-0.0.1.dist-info/metadata.json
rijksdriehoek-0.0.1.dist-info/top_level.txt
