Metadata-Version: 2.0
Name: rijksdriehoek
Version: 0.0.1
Summary: A Rijksdriehoek (EPSG:28992) to WGS'84 conversion utility
Home-page: https://gitea.hillebrand.io/Flippylosaurus/python-rijksdriehoek
Author: flimpie
Author-email: python-packaging@hillebrand.io
License: UNKNOWN
Platform: UNKNOWN
Classifier: Programming Language :: Python :: 3
Classifier: Development Status :: 4 - Beta
Classifier: License :: OSI Approved :: GNU General Public License v3 (GPLv3)
Classifier: Operating System :: OS Independent
